pybktreespellchecker
