Metadata-Version: 1.0
Name: pybktreespellchecker
Version: 0.0.5
Summary: Python implementation of BK-tree and Levenshtein distance to perform spell checking
Home-page: https://github.com/tomasrasymas/pybktree-spell-checker
Author: Tomas Rasymas
Author-email: tomas.rasymas@gmail.com
License: MIT
Platform: UNKNOWN
